dbConnect/__init__.py
dbConnect/dbConnect.py
dbConnect-2.1.data/scripts/dbConnect.py
dbConnect-2.1.dist-info/DESCRIPTION.rst
dbConnect-2.1.dist-info/METADATA
dbConnect-2.1.dist-info/RECORD
dbConnect-2.1.dist-info/WHEEL
dbConnect-2.1.dist-info/metadata.json
dbConnect-2.1.dist-info/top_level.txt
